gradient_statsd/__init__.py
gradient_statsd/client.py
gradient_statsd-1.0.1.dist-info/LICENSE
gradient_statsd-1.0.1.dist-info/METADATA
gradient_statsd-1.0.1.dist-info/WHEEL
gradient_statsd-1.0.1.dist-info/top_level.txt
gradient_statsd-1.0.1.dist-info/RECORD
